xlsx_to_handontable/__init__.py
xlsx_to_handontable/check_unique.py
xlsx_to_handontable/cli.py
xlsx_to_handontable/count_col.py
xlsx_to_handontable/values_rows_to_js_nested_headers.py
xlsx_to_handontable/xlsx_to_configs_samples.py
xlsx_to_handontable-0.2.0.dist-info/DESCRIPTION.rst
xlsx_to_handontable-0.2.0.dist-info/METADATA
xlsx_to_handontable-0.2.0.dist-info/RECORD
xlsx_to_handontable-0.2.0.dist-info/WHEEL
xlsx_to_handontable-0.2.0.dist-info/entry_points.txt
xlsx_to_handontable-0.2.0.dist-info/metadata.json
xlsx_to_handontable-0.2.0.dist-info/top_level.txt
