Metadata-Version: 2.0
Name: xlsx-to-handontable
Version: 0.2.0
Summary: xlsx_to_handontable
Home-page: https://github.com/fingul/xlsx_to_handontable
Author: Fingul
Author-email: fingul@gmail.com
License: MIT license
Keywords: xlsx_to_handontable
Platform: UNKNOWN
Classifier: Development Status :: 2 - Pre-Alpha
Classifier: Intended Audience :: Developers
Classifier: License :: OSI Approved :: MIT License
Classifier: Natural Language :: English
Classifier: Programming Language :: Python :: 2
Classifier: Programming Language :: Python :: 2.6
Classifier: Programming Language :: Python :: 2.7
Classifier: Programming Language :: Python :: 3
Classifier: Programming Language :: Python :: 3.3
Classifier: Programming Language :: Python :: 3.4
Classifier: Programming Language :: Python :: 3.5
Requires-Dist: Click (>=6.0)
Requires-Dist: openpyxl
Requires-Dist: pyyaml
Requires-Dist: yaml-dump
